halma_game/__init__.py
halma_game/__main__.py
halma_game/halma_model.py
halma_game/halma_player.py
halma_game/halma_player_01_A.py
halma_game/halma_player_01_B.py
halma_game/halma_player_02_A.py
halma_game/halma_player_02_B.py
halma_game/halma_player_03_A.py
halma_game/halma_player_03_B.py
halma_game/halma_player_04_A.py
halma_game/halma_player_04_B.py
halma_game/halma_player_human.py
halma_game-0.3.6.dist-info/LICENSE
halma_game-0.3.6.dist-info/METADATA
halma_game-0.3.6.dist-info/WHEEL
halma_game-0.3.6.dist-info/top_level.txt
halma_game-0.3.6.dist-info/RECORD
