Metadata-Version: 2.1
Name: halma-game
Version: 0.3.6
Summary: Halma game created with python (pygame)
Home-page: https://github.com/rasisbuldan/halma_game
Author: Rasis Syauqi Buldan
Author-email: rasisbuldan@gmail.com
License: MIT
Download-URL: https://github.com/rasisbuldan/halma_game/archive/v0.3.6.tar.gz
Platform: UNKNOWN
Classifier: Programming Language :: Python :: 3
Classifier: License :: OSI Approved :: MIT License
Classifier: Operating System :: OS Independent
Requires-Python: >=3.6
Requires-Dist: pygame
